cosmos_cli.py
cosmos_cli-0.13.dist-info/LICENSE
cosmos_cli-0.13.dist-info/METADATA
cosmos_cli-0.13.dist-info/WHEEL
cosmos_cli-0.13.dist-info/entry_points.txt
cosmos_cli-0.13.dist-info/top_level.txt
cosmos_cli-0.13.dist-info/RECORD
