Metadata-Version: 2.1
Name: cosmos-cli
Version: 0.13
Summary: UNKNOWN
Home-page: https://github.com/gopuff/cosmos-cli
Maintainer: Ethan McCreadie
Maintainer-email: ethan.mccreadie@gopuff.com
License: UNKNOWN
Platform: UNKNOWN
Requires-Python: >=3.4
Requires-Dist: cmd2 (>=0.9.7)
Requires-Dist: pydocumentdb
Requires-Dist: pygments
Requires-Dist: termcolor
